{
  "antler": {"assoc": "אנטלר – אנט-לר, כמו קרן שבולטת מהאנט (אנטילופה) לרוחב!", "sentence": "The deer's antler was caught in the fence.|קרן הצבי נתקעה בגדר."},
  "automobile": {"assoc": "אוטומוביל – אוטו שנוסע מוביל את עצמו לבד!", "sentence": "The automobile broke down on the highway.|האוטו התקלקל על הכביש המהיר."},
  "bass": {"assoc": "בס – הצליל הבס כל כך נמוך שהוא בס-ביחד עם הרצפה!", "sentence": "The bass guitar gave the song a deep sound.|גיטרת הבס נתנה לשיר צליל עמוק."},
  "bead": {"assoc": "ביד – חרוז בידיה של סבתא שמחרזת שרשרת!", "sentence": "She lost a bead from her necklace.|היא איבדה חרוז מהשרשרת שלה."},
  "beak": {"assoc": "ביק – ציפור עם ביק (מקור) שמנקרת ביקבוק!", "sentence": "The parrot used its beak to crack the nut.|התוכי השתמש במקורו לפצח את האגוז."},
  "bee": {"assoc": "בי – הדבורה אומרת לך בי-בי לפני שהיא עוקצת!", "sentence": "A bee landed on the flower.|דבורה נחתה על הפרח."},
  "bell": {"assoc": "בל – הפעמון עושה בל-בל-בל כשמצלצלים!", "sentence": "The church bell rang at noon.|פעמון הכנסייה צלצל בצהריים."},
  "berry": {"assoc": "בֵרי – תאכל גרגרי יער ותהיה בֵרי (ברי) מאושר!", "sentence": "She picked a wild berry from the bush.|היא קטפה גרגיר יער מהשיח."},
  "blade": {"assoc": "בלייד – ה-בלייד (להב) של הסכין חד כמו השם!", "sentence": "The blade of the knife was very sharp.|להב הסכין היה חד מאוד."},
  "blanket": {"assoc": "בלנקט – בלי קט (קר) כי יש לי שמיכה!", "sentence": "She wrapped herself in a warm blanket.|היא עטפה את עצמה בשמיכה חמה."},
  "bleak": {"assoc": "בליק – מבט בליק (חטוף) על הנוף העגום בחורף!", "sentence": "The winter landscape looked bleak and cold.|נוף החורף נראה עגום וקר."},
  "blew": {"assoc": "בלו – הרוח בלו-בלו ונשבה חזק כחלום כחול!", "sentence": "The wind blew all the leaves away.|הרוח נשבה ופיזרה את כל העלים."},
  "brick": {"assoc": "בריק – לבנה שבריק-בריק בוהקת אחרי הגשם!", "sentence": "The house was built with red bricks.|הבית נבנה מלבנים אדומות."},
  "bully": {"assoc": "בולי – הבריון בולי (בולע) את כל השמחה בכיתה!", "sentence": "The bully scared the younger kids at school.|הבריון הפחיד את הילדים הקטנים בבית הספר."},
  "butterfly": {"assoc": "באטרפליי – חמאה (באטר) עפה (פליי) – זה פרפר!", "sentence": "A colorful butterfly landed on my hand.|פרפר צבעוני נחת על ידי."},
  "cadaver": {"assoc": "קדאבר – קד-אבר, כמו גופה שקדה לפני שאברה מהעולם!", "sentence": "The medical students studied a cadaver.|סטודנטים לרפואה חקרו גופה."},
  "camel": {"assoc": "קמל – הגמל קמל (כמעט קמל) מצמא אבל שורד!", "sentence": "The camel walked across the hot desert.|הגמל הלך על פני המדבר החם."},
  "candy": {"assoc": "קנדי – בקנדה מוכרים ממתקים בכל פינה!", "sentence": "The child asked for a piece of candy.|הילד ביקש חתיכת ממתק."},
  "canvass": {"assoc": "קנבס – כמו לצייר על קנבס – לסקור כל פינה!", "sentence": "The politician went to canvass the neighborhood.|הפוליטיקאי יצא לסקור את השכונה."},
  "carpet": {"assoc": "קרפט – שטיח שעשוי בקרפט (מלאכה) עדינה!", "sentence": "The living room had a soft carpet.|בסלון היה שטיח רך."},
  "cash": {"assoc": "קש – מזומן קש-קש, כי כסף עושה רעש של קשקוש!", "sentence": "I paid for the groceries with cash.|שילמתי על המכולת במזומן."},
  "cashier": {"assoc": "קשיר – הקופאי קשיר (קשור) לקופה כל היום!", "sentence": "The cashier smiled and gave me my change.|הקופאי חייך ונתן לי את העודף."},
  "casino": {"assoc": "קזינו – קזינו זה מקום שבו כסף נו... נעלם!", "sentence": "We spent the evening at the casino.|בילינו את הערב בקזינו."},
  "caterpillar": {"assoc": "קטרפילר – קטר-פילר, כמו רכבת זחל שמתפתלת!", "sentence": "A caterpillar slowly crawled up the leaf.|זחל התפתל לאט על העלה."},
  "caviar": {"assoc": "קוויאר – קוויאר זה יקר כי אמרת וואי-אר יקר!", "sentence": "They served caviar at the fancy dinner.|הגישו קוויאר בארוחת הערב המפוארת."},
  "cereal": {"assoc": "סיריאל – סדרת (סיריאל) בוקר עם קערת דגני בוקר!", "sentence": "I eat cereal with milk every morning.|אני אוכל דגני בוקר עם חלב כל בוקר."},
  "cigarette": {"assoc": "סיגרט – סיגריה קטנה = סיגרט, קטנה אבל מסוכנת!", "sentence": "He threw the cigarette on the ground.|הוא זרק את הסיגריה לקרקע."},
  "citrus": {"assoc": "סיטרוס – סיט-רוס, פרי הדר שגורם לך לסטות מהדיאטה!", "sentence": "Lemon is a common citrus fruit.|לימון הוא פרי הדר נפוץ."},
  "clay": {"assoc": "קליי – חימר קליי שניתן לגלגל כמו כדור!", "sentence": "The artist shaped the clay into a bowl.|האמן עיצב את החימר לקערה."},
  "cloud": {"assoc": "קלאוד – ענן קלאוד שמאחסן גשם בשמיים!", "sentence": "A dark cloud covered the sun.|ענן כהה כיסה את השמש."},
  "club": {"assoc": "קלאב – קלאב זה מועדון שבו כולם קלאס!", "sentence": "She joined a book club last month.|היא הצטרפה למועדון ספרים בחודש שעבר."},
  "cockroach": {"assoc": "קוקרוץ' – קוק-רוץ, המקק רץ מהירות כשאתה מדליק אור!", "sentence": "A cockroach ran across the kitchen floor.|מקק רץ על רצפת המטבח."},
  "coffin": {"assoc": "קופין – ארון מתים קו-פין, גמרת פה!", "sentence": "The coffin was carried by six people.|ארון המתים נשא על ידי שישה אנשים."},
  "cologne": {"assoc": "קולון – קולון זה בושם גברי שמריחים מקילומטר!", "sentence": "He put on cologne before the date.|הוא מרח קולון לפני הדייט."},
  "compost": {"assoc": "קומפוסט – קום-פוסט, קום בבוקר ותן פוסט לפח הזבל האורגני!", "sentence": "We put vegetable scraps in the compost.|שמנו שאריות ירקות בזבל האורגני."},
  "conductor": {"assoc": "קונדקטור – קון-דקטור, המנצח קונה דקות מהתזמורת!", "sentence": "The conductor raised his baton and the music began.|המנצח הרים את הבטון והמוזיקה החלה."},
  "conquistador": {"assoc": "קונקיסטדור – קונה-קיסר-דור, כובש שקונה ממלכות לדורות!", "sentence": "The conquistador sailed to the new world.|הכובש שט לעולם החדש."},
  "consonant": {"assoc": "קונסוננט – קון-סון-נט, עיצור שקונה צליל נטו בלי תנועה!", "sentence": "The letter B is a consonant.|האות B היא עיצור."},
  "coop": {"assoc": "קופ – הלול קופ-קופ, עוף שכלוא בקופסה!", "sentence": "The chickens sleep in the coop at night.|התרנגולות ישנות בלול בלילה."},
  "copper": {"assoc": "קופר – נחושת קופר, כמו מטבע קופרי ישן!", "sentence": "The pipe was made of copper.|הצינור היה עשוי נחושת."},
  "cotton": {"assoc": "קוטון – כותנה קוטון, רכה כמו כוט (חתלתול) קטן!", "sentence": "The shirt was made of soft cotton.|החולצה הייתה עשויה כותנה רכה."},
  "cougar": {"assoc": "קוגר – קוגר טורף שקופץ כמו קו-גר (גר על הקו)!", "sentence": "A cougar was spotted near the hiking trail.|פומה נצפתה ליד שביל הטיול."},
  "coupon": {"assoc": "קופון – קופון, קו-פון, שים בקופה ותחסוך!", "sentence": "I used a coupon to get a discount.|השתמשתי בקופון לקבל הנחה."},
  "cucumber": {"assoc": "קיוקמבר – קיו (תור) לקנות קמבר (מלפפון) בשוק!", "sentence": "She sliced a cucumber for the salad.|היא פרסה מלפפון לסלט."},
  "culminate": {"assoc": "קולמינייט – קול-מינייט, הכל מגיע לשיא ברגע האחרון!", "sentence": "Years of hard work culminate in success.|שנים של עבודה קשה מגיעות לשיאן בהצלחה."},
  "czar": {"assoc": "צאר – צאר רוסי שצועק צ-א-ר על כולם!", "sentence": "The czar ruled Russia for many years.|הצאר שלט ברוסיה שנים רבות."},
  "dart": {"assoc": "דארט – חץ דארט שדאר-ט (דהר) לתוך המטרה!", "sentence": "He threw a dart at the board.|הוא זרק חץ לעבר הלוח."},
  "date": {"assoc": "דייט – תאריך, תמר ודייט – שלושה ב-דייט אחד!", "sentence": "We went on a date to the restaurant.|יצאנו לדייט במסעדה."},
  "Dead Sea": {"assoc": "ים המלח – ים כל כך מלוח שאפילו דגים מתו מזה!", "sentence": "The Dead Sea is the saltiest lake in the world.|ים המלח הוא האגם המלוח ביותר בעולם."},
  "denominator": {"assoc": "דנומינטור – דנום-ינ-טור, המכנה שמינה את כל השברים!", "sentence": "The denominator in this fraction is four.|המכנה בשבר הזה הוא ארבע."},
  "dental": {"assoc": "דנטל – דנ-טל, דנטיסט טל שעובד על שיניים!", "sentence": "She has a dental appointment tomorrow.|יש לה תור לרופא שיניים מחר."},
  "dentist": {"assoc": "דנטיסט – דנ-טיסט, רופא שיניים שתמיד מטיס אותך לכיסא!", "sentence": "The dentist checked my teeth carefully.|רופא השיניים בדק את שיניי בקפידה."},
  "diary": {"assoc": "דיירי – דיירי (כמו דייר), היומן גר אצלך בסוד!", "sentence": "She writes in her diary every night.|היא כותבת ביומנה כל לילה."},
  "dictator": {"assoc": "דיקטטור – דיקטטור זה מישהו שדיקטט לכולם מה לעשות!", "sentence": "The dictator ruled the country with fear.|הדיקטטור שלט במדינה באמצעות פחד."},
  "dilemma": {"assoc": "דילמה – די-למה? די! למה יש לי בעיה כזו!", "sentence": "Choosing between the two jobs was a real dilemma.|הבחירה בין שני המשרות הייתה דילמה אמיתית."},
  "diurnal": {"assoc": "דיורנל – דיור-נל, חיות יומיות שדואגות לדיור ביום!", "sentence": "Most birds are diurnal and sleep at night.|רוב הציפורים הן יומיות וישנות בלילה."},
  "divorce": {"assoc": "דיבורס – די-בורס, די! נמאס לי, אני רוצה גירושין!", "sentence": "They decided to get a divorce after ten years.|הם החליטו להתגרש אחרי עשר שנים."},
  "doorstep": {"assoc": "דורסטפ – דור-סטפ, צעד לדור חדש מהמפתן!", "sentence": "A package was left on the doorstep.|חבילה הושארה על מפתן הדלת."},
  "dovecote": {"assoc": "דאבקוט – דאב-קוט, שובך שבו יונים קוטות (מקרקרות) בשקט!", "sentence": "The old dovecote stood in the garden.|השובך הישן עמד בגינה."},
  "dust": {"assoc": "דאסט – דאסט זה אבק שמדאיב אותך כשמנקים!", "sentence": "There was dust on every shelf.|היה אבק על כל מדף."},
  "Dutch": {"assoc": "דאץ' – הולנדי דאץ', כמו Going Dutch – כל אחד משלם!", "sentence": "My friend is Dutch and speaks Dutch.|חברי הולנדי ומדבר הולנדית."},
  "dwarf": {"assoc": "דוורף – גמד דוורף, כמו הגמדים של שלגיה!", "sentence": "The dwarf in the story had a long beard.|לגמד בסיפור הייתה זקן ארוכה."},
  "dwindle": {"assoc": "דווינדל – דו-ווינדל, הכסף דו-ווינדל (כפול הידלדל) מהר!", "sentence": "Our water supply began to dwindle.|אספקת המים שלנו החלה להידלדל."},
  "eagle": {"assoc": "איגל – נשר איגל, כמו Eagle Scout – גאה וחזק!", "sentence": "The eagle soared high above the mountains.|הנשר ריחף גבוה מעל ההרים."},
  "echo": {"assoc": "אקו – הד אקו-אקו-אקו, שומע את עצמך שלוש פעמים!", "sentence": "His voice made an echo in the cave.|קולו יצר הד במערה."},
  "eel": {"assoc": "איל – צלופח איל, חלקלק כמו שם קצר!", "sentence": "The eel hid under a rock in the river.|הצלופח התחבא מתחת לאבן בנהר."},
  "elephant": {"assoc": "אלפנט – אל-פנט, פיל שאל אותך פנטה (כמה גדול הוא)!", "sentence": "The elephant splashed water with its trunk.|הפיל ריסס מים עם חדקו."},
  "exotic": {"assoc": "אקזוטי – אקס-זוטי, מקום שאקס שלך נסע אליו – אקזוטי!", "sentence": "The market sold exotic fruits from the tropics.|השוק מכר פירות אקזוטיים מהטרופיקה."},
  "fairy": {"assoc": "פיירי – פיה-ירי, פיה שיורה ניצוצות קסם!", "sentence": "The fairy waved her magic wand.|הפיה הניפה את שרביט הקסמים שלה."},
  "fairytale": {"assoc": "פיירי-טייל – פיה-טייל, אגדה שיש בה פיה שמטיילת!", "sentence": "Cinderella is a famous fairytale.|סינדרלה היא אגדה מפורסמת."},
  "fan": {"assoc": "פן – מאוורר פן, כמו פן-פן שמנפנף אוויר!", "sentence": "The fan cooled the room on the hot day.|המאוורר קירר את החדר ביום החם."},
  "fancy": {"assoc": "פנסי – פנסי-פנסי, מגונדר כמו מישהו שחושב שהוא פנסי!", "sentence": "She wore a fancy dress to the party.|היא לבשה שמלה מגונדרת למסיבה."},
  "fashion": {"assoc": "פשן – אופנה פשן, כמו פאשניסטה שמשגעת את כולם!", "sentence": "She works in the fashion industry.|היא עובדת בתעשיית האופנה."},
  "filmmaker": {"assoc": "פילם-מייקר – פילם עושה, יוצר סרטים שעושה פילמים!", "sentence": "The filmmaker won an award for his documentary.|יוצר הסרטים זכה בפרס על הסרט התיעודי שלו."},
  "filter": {"assoc": "פילטר – פילטר מסנן את מה שלא רוצים לראות!", "sentence": "The filter removed the dirt from the water.|המסנן הסיר את הלכלוך מהמים."},
  "fisherman": {"assoc": "פישרמן – פיש-ר-מן, דייג שעושה פיש (דג) כל היום!", "sentence": "The fisherman caught a large fish at dawn.|הדייג תפס דג גדול עם שחר."},
  "fishing": {"assoc": "פישינג – פיש-ינג, דיג זה לחכות לפיש (דג) בסבלנות!", "sentence": "We went fishing by the lake on Sunday.|יצאנו לדיג ליד האגם ביום ראשון."},
  "flimsy": {"assoc": "פלימזי – פלים-זי, כמו סרט פלים שביר שנקרע בקלות!", "sentence": "The flimsy tent collapsed in the wind.|האוהל השביר קרס ברוח."},
  "folk": {"assoc": "פולק – פולק זה עממי, כמו מוזיקת עם של פולקים!", "sentence": "They danced to traditional folk music.|הם רקדו למוזיקת עם מסורתית."},
  "folklore": {"assoc": "פולקלור – פולק-לור, לור (ידע) עממי שהפולק מעביר דור לדור!", "sentence": "The story comes from old local folklore.|הסיפור מגיע מהפולקלור המקומי הישן."}
}