{
  "mass": {"assoc": "מאס – כל כך המון אנשים שכבר מאסת בהם!", "sentence": "A mass of people gathered in the square.|המון אנשים התכנסו בכיכר."},
  "merger": {"assoc": "מרג'ר – מיזוג של שני מרגים לתוך קדרה אחת.", "sentence": "The merger of the two companies was successful.|המיזוג של שתי החברות הצליח."},
  "odd": {"assoc": "אוד – מוזר שאוד (עץ) הוא כלי נגינה, לא אי-זוגי!", "sentence": "It was an odd request to make at midnight.|זה היה בקשה מוזרה לעשות בחצות."},
  "opportunity": {"assoc": "אופורטיוניטי – הזדמנות שמרובר פגש אופורטיוניסט!", "sentence": "This job is a great opportunity for growth.|עבודה זו היא הזדמנות מצוינת לצמיחה."},
  "organic": {"assoc": "אורגניק – אורגן (עוגב) שמנגן מוזיקה טבעית וגדל בשדה!", "sentence": "She only buys organic vegetables from the market.|היא קונה רק ירקות אורגניים מהשוק."},
  "overlaps": {"assoc": "אוברלפס – עובר ולפ (leap) מעל וחופף את הגבול!", "sentence": "Our work schedules overlap on Tuesdays.|לוחות הזמנים שלנו חופפים בימי שלישי."},
  "own": {"assoc": "און – זה שלי, אני הבעלים, אני עצמי – אוּן!", "sentence": "She owns her own apartment in the city.|היא בעלת דירה משלה בעיר."},
  "owner": {"assoc": "אונר – האונר (הכבוד) שייך לבעלים!", "sentence": "The owner of the store arrived early.|בעל החנות הגיע מוקדם."},
  "paramount": {"assoc": "פראמאונט – הר (mount) עליון בראש פיסגת החשיבות!", "sentence": "Safety is of paramount importance in this job.|בטיחות היא בעלת חשיבות עליונה בעבודה זו."},
  "pedestrian": {"assoc": "פדסטריאן – פדס (כף רגל) + סטרין = הולך רגל שצועד בסטריאו!", "sentence": "The pedestrian crossed the road carefully.|הולך הרגל חצה את הכביש בזהירות."},
  "perhaps": {"assoc": "פרהפס – פר (פרה) הפסה – אולי הפרה הפסידה?", "sentence": "Perhaps we should try a different approach.|אולי עלינו לנסות גישה אחרת."},
  "planet": {"assoc": "פלנט – פלנטה, כמו פלן (תכנן) לטוס לכוכב לכת!", "sentence": "Earth is the only known planet with life.|כדור הארץ הוא כוכב הלכת היחיד הידוע עם חיים."},
  "poll": {"assoc": "פול – פול (שעועית) שנסקרת – כמה אוהבים פול?", "sentence": "The latest poll shows the candidate is leading.|הסקר האחרון מראה שהמועמד מוביל."},
  "post": {"assoc": "פוסט – פוסטר על עמוד הדואר שפרסמו ברחוב!", "sentence": "She posted a letter to her grandmother.|היא שלחה מכתב לסבתא שלה בדואר."},
  "postage": {"assoc": "פוסטאג' – פוסט + אג' (אגרה) = דמי משלוח לפוסט!", "sentence": "The postage for this package is very expensive.|דמי המשלוח לחבילה זו יקרים מאוד."},
  "presume": {"assoc": "פריזום – פרי + זום = הניח שהפרי יתקרב בזום!", "sentence": "I presume you already know the answer.|אני מניח שאתה כבר יודע את התשובה."},
  "priest": {"assoc": "פריסט – פרי + סט = הכומר מגיש סט פירות בכנסייה!", "sentence": "The priest led the morning prayer service.|הכומר הוביל את תפילת הבוקר."},
  "publication": {"assoc": "פבליקיישן – פבליק (ציבור) + ציוּן = פרסום לציבור!", "sentence": "The publication of her book was a huge success.|פרסום ספרה היה הצלחה גדולה."},
  "publicized": {"assoc": "פבליסייזד – פבליק + סייז = פורסם לציבור בגדול!", "sentence": "The event was widely publicized in the media.|האירוע פורסם באופן נרחב בתקשורת."},
  "publisher": {"assoc": "פבלישר – פבליש (לפרסם) + ר = המוציא לאור שמוציא ספרים לשוק!", "sentence": "The publisher agreed to print her novel.|המוציא לאור הסכים להדפיס את הרומן שלה."},
  "qualify": {"assoc": "קוואליפיי – קוואלי (איכות) + פיי (לשלם) = לשלם באיכות כדי להכשיר!", "sentence": "She studied hard to qualify as a doctor.|היא למדה קשה כדי להכשיר עצמה כרופאה."},
  "quarter": {"assoc": "קווארטר – קווארטט של ארבעה = רבע מהם מנגן!", "sentence": "He ate a quarter of the pizza himself.|הוא אכל רבע מהפיצה לבד."},
  "raw": {"assoc": "רו – ראו את הבשר הגולמי – הוא עוד נא!", "sentence": "The chef prepared a dish with raw fish.|השף הכין מנה עם דג נא."},
  "recognition": {"assoc": "רקוגניישן – ריקוגניציה = הכרה! מזהים אותך!", "sentence": "He received recognition for his hard work.|הוא קיבל הכרה על עבודתו הקשה."},
  "record": {"assoc": "רקורד – שיא! שובר רקורד ברשומה החדשה שהוקלטה!", "sentence": "She broke the world record for the long jump.|היא שברה את שיא העולם בקפיצה לרוחק."},
  "recreate": {"assoc": "ריקריאייט – ריקריאציה = לבלות ולשחזר את הכיף!", "sentence": "They tried to recreate the famous recipe.|הם ניסו לשחזר את המתכון המפורסם."},
  "relax": {"assoc": "רילקס – רי + לקס (שרוך רפוי) = להירגע ולהרפות!", "sentence": "After work, she likes to relax with a book.|אחרי העבודה, היא אוהבת להירגע עם ספר."},
  "remains": {"assoc": "רימיינס – ריי + מיין (שלי) = מה שנשאר זה שלי, שרידים!", "sentence": "The remains of the old castle still stand.|שרידי הטירה הישנה עדיין עומדים."},
  "remove": {"assoc": "רימוב – רי + מוב (לזוז) = לזוז שוב ולהסיר!", "sentence": "Please remove your shoes before entering.|אנא הסר את נעליך לפני הכניסה."},
  "renew": {"assoc": "ריניו – רי + ניו (חדש) = לחדש ולהפוך לחדש שוב!", "sentence": "He needs to renew his passport before the trip.|הוא צריך לחדש את הדרכון שלו לפני הטיול."},
  "renown": {"assoc": "ריניאון – רי + נאון (נאון זוהר) = פרסום שזוהר שוב ושוב!", "sentence": "The scientist gained renown for her discoveries.|המדענית זכתה לפרסום בזכות תגליותיה."},
  "repair": {"assoc": "ריפר – ריפא + ר = לתקן ולרפא את הבעיה!", "sentence": "The mechanic came to repair the broken car.|המכונאי הגיע לתקן את המכונית השבורה."},
  "replace": {"assoc": "ריפלייס – רי + פלייס (מקום) = לשים מחדש ולהחליף!", "sentence": "We need to replace the old light bulb.|אנחנו צריכים להחליף את הנורה הישנה."},
  "replacement": {"assoc": "ריפלייסמנט – החלפה שמחליפה את המקום!", "sentence": "The replacement part arrived within two days.|חלק התחליף הגיע תוך יומיים."},
  "rescue": {"assoc": "רסקיו – רס + קיו (תור) = עמד בתור להצלה בחילוץ!", "sentence": "The firefighters performed a daring rescue.|כבאי האש ביצעו חילוץ נועז."},
  "resident": {"assoc": "רזידנט – רזידנציה = תושב שגר ברזידנציה!", "sentence": "She has been a resident of this city for years.|היא תושבת העיר הזו כבר שנים."},
  "resource": {"assoc": "ריסורס – רי + סורס (מקור) = מקור משאב חוזר!", "sentence": "Water is a precious natural resource.|מים הם משאב טבעי יקר ערך."},
  "resourceful": {"assoc": "ריסורספול – מלא (פול) במשאבים ותושייה!", "sentence": "The resourceful student solved the problem quickly.|הסטודנט בעל התושייה פתר את הבעיה במהירות."},
  "restrain": {"assoc": "ריסטריין – רי + סטריין (מאמץ) = למאמץ שוב כדי לרסן!", "sentence": "She had to restrain herself from laughing.|היא נאלצה לרסן עצמה מצחוק."},
  "retain": {"assoc": "ריטיין – רי + טיין (לשמור) = לשמר ולהחזיק שוב!", "sentence": "The company wants to retain its best employees.|החברה רוצה לשמר את עובדיה הטובים ביותר."},
  "retrieve": {"assoc": "ריטריב – רי + טריב (שבט) = השבט אחזר את החפץ!", "sentence": "The dog was trained to retrieve the ball.|הכלב אומן לאחזר את הכדור."},
  "revenue": {"assoc": "רוונייו – רב + ניו = הכנסות חדשות ורבות!", "sentence": "The company's revenue increased this year.|הכנסות החברה גדלו השנה."},
  "route": {"assoc": "ראוט – רוט (שורש) של מסלול שמוביל לדרך!", "sentence": "We took the scenic route through the mountains.|נסענו במסלול הנופי דרך ההרים."},
  "satisfaction": {"assoc": "סטיספקשן – סטיס + פקשן = שביעות רצון שמרווה את הפקשן (תאבון)!", "sentence": "She felt deep satisfaction after finishing the project.|היא הרגישה שביעות רצון עמוקה לאחר סיום הפרויקט."},
  "sensitivity": {"assoc": "סנסיטיביטי – סנסי + טיב = רגישות לטיב ולתחושה!", "sentence": "Her sensitivity to others makes her a good friend.|הרגישות שלה לאחרים הופכת אותה לחברה טובה."},
  "sentence": {"assoc": "סנטנס – סנט (קדוש) + נס = גזר דין קדוש שהוא נס!", "sentence": "The judge read the sentence in court.|השופט קרא את גזר הדין בבית המשפט."},
  "servant": {"assoc": "סרבנט – סרב + נט = העבד שסירב ברשת נתפס!", "sentence": "The servant brought tea to the guests.|המשרת הביא תה לאורחים."},
  "serve": {"assoc": "סרב – שמש בסרב = לשרת את כולם!", "sentence": "He was proud to serve his country.|הוא היה גאה לשרת את ארצו."},
  "sharp": {"assoc": "שארפ – שר + פ = השר החד שחורז בחריפות!", "sentence": "Be careful, this knife is very sharp.|היזהר, הסכין הזה חד מאוד."},
  "sheer": {"assoc": "שיר – שיר גרידא, מוחלט – שיר טהור!", "sentence": "It was sheer luck that he survived.|זה היה מזל גרידא שהוא שרד."},
  "skepticism": {"assoc": "ספקטיסיזם – ספק + טיק = ספקן שיש לו טיק מרוב ספקנות!", "sentence": "His skepticism about the plan was understandable.|הספקנות שלו לגבי התוכנית הייתה מובנת."},
  "spare": {"assoc": "ספר – ספר חלף שחוסך מקום על המדף!", "sentence": "Do you have a spare key for the door?|יש לך מפתח חלף לדלת?"},
  "specify": {"assoc": "ספסיפיי – ספסיפי = לפרט ולציין בדיוק!", "sentence": "Please specify your preferred delivery date.|אנא פרט את תאריך המשלוח המועדף עליך."},
  "spectator": {"assoc": "ספקטייטר – ספקטקל + טייטר = צופה בתיאטרון!", "sentence": "The spectators cheered loudly at the game.|הצופים עודדו בקול רם במשחק."},
  "speech": {"assoc": "ספיץ' – ספיץ (כלב) נאם נאום ב-דיבור!", "sentence": "The president gave an inspiring speech.|הנשיא נשא נאום מעורר השראה."},
  "spoil": {"assoc": "ספויל – ספוג + אויל (שמן) = ספוג שמן שמקלקל ומפנק!", "sentence": "Don't spoil your appetite before dinner.|אל תקלקל את התיאבון שלך לפני הארוחה."},
  "staple": {"assoc": "סטייפל – סטייפלר = סיכת נייר עיקרית ובסיסית!", "sentence": "Rice is a staple food in many countries.|אורז הוא מזון עיקרי במדינות רבות."},
  "stomach": {"assoc": "סטומק – סטו + מק = הבטן שמקבלת את התבשיל (סטו)!", "sentence": "He had a stomachache after eating too much.|הוא סבל מכאב בטן אחרי שאכל יותר מדי."},
  "strategy": {"assoc": "סטרטג'י – סטרטג = אסטרטגיה של סטרטג מנצח!", "sentence": "The team developed a new strategy to win.|הצוות פיתח אסטרטגיה חדשה לניצחון."},
  "subdue": {"assoc": "סבדיו – סב + דיו = הסב כבש ולכד בדיו!", "sentence": "The police managed to subdue the suspect.|המשטרה הצליחה להכניע את החשוד."},
  "suitable": {"assoc": "סיוטבל – סיוט + בל = לא סיוט! זה מתאים ובלי בלגן!", "sentence": "This dress is suitable for a formal event.|שמלה זו מתאימה לאירוע רשמי."},
  "superb": {"assoc": "סיופרב – סיופר + ב = נהדר בסיופרמן!", "sentence": "The meal at the restaurant was simply superb.|הארוחה במסעדה הייתה פשוט נהדרת."},
  "suppression": {"assoc": "ספרשן – סופר + שן = הסופר דיכא את השן הכואבת!", "sentence": "The suppression of the protest shocked the world.|דיכוי המחאה זעזע את העולם."},
  "symbol": {"assoc": "סימבול – סים + בול = בול דואר הוא סמל!", "sentence": "The dove is a symbol of peace.|היונה היא סמל של שלום."},
  "symbolize": {"assoc": "סימבולייז – סמל שמסמל ומסמל שוב!", "sentence": "The flag symbolizes the nation's unity.|הדגל מסמל את אחדות האומה."},
  "take place": {"assoc": "טייק פלייס – קח את המקום = זה קורה ומתרחש!", "sentence": "The ceremony will take place on Friday evening.|הטקס יתקיים ביום שישי בערב."},
  "temple": {"assoc": "טמפל – טמפ (חום) + ל = המקדש שחם ברקה בצהריים!", "sentence": "The ancient temple was built thousands of years ago.|המקדש העתיק נבנה לפני אלפי שנים."},
  "terms": {"assoc": "טרמס – טרם + ס = תנאים שצריך לקרוא לפני שחותמים!", "sentence": "Please read the terms and conditions carefully.|אנא קרא את התנאים וההגבלות בעיון."},
  "thousand": {"assoc": "תאוזנד – תאו + זנד = אלף תאואים בזנדר!", "sentence": "Over a thousand people attended the concert.|למעלה מאלף אנשים השתתפו בקונצרט."},
  "tormented": {"assoc": "טורמנטד – טורמנט = מעונה שמרגיש כמו בטורניר כאב!", "sentence": "He was tormented by guilt for years.|הוא היה מעונה בייסורי אשמה שנים רבות."},
  "tour": {"assoc": "טור – טור (שורה) של סיורים בעיר!", "sentence": "They went on a tour of the old city.|הם יצאו לסיור בעיר העתיקה."},
  "tourist": {"assoc": "טוריסט – טור + ריסט = תייר שמסייר ומנוח!", "sentence": "The tourist asked for directions to the museum.|התייר ביקש הוראות הגעה למוזיאון."},
  "trust": {"assoc": "טראסט – טרם + סט = אמון שעדיין לא הוּגדר אך בוטחים בו!", "sentence": "She trusted her friend with her secret.|היא בטחה בחברתה עם הסוד שלה."},
  "typically": {"assoc": "טיפיקלי – טיפוסי + לי = בדרך כלל זה טיפוסי בשבילי!", "sentence": "He typically arrives at work before eight.|הוא בדרך כלל מגיע לעבודה לפני שמונה."},
  "underlies": {"assoc": "אנדרלייז – אנדר (מתחת) + לייז = עומד מתחת ובסיס לכל!", "sentence": "Fear often underlies aggressive behavior.|פחד עומד לעתים קרובות מאחורי התנהגות תוקפנית."},
  "unemployed": {"assoc": "אנמפלוייד – אן + אמפלוי = לא מועסק, מובטל בלי עבודה!", "sentence": "He has been unemployed for six months.|הוא מובטל כבר שישה חודשים."},
  "unexplored": {"assoc": "אנאקספלורד – אן + אקספלור = לא נחקר, טרה אינקוגניטה!", "sentence": "Much of the ocean floor remains unexplored.|רוב קרקעית הים נשארת לא נחקרת."},
  "unfamiliar": {"assoc": "אנפמיליאר – אן + פמיליה = לא מהמשפחה = לא מוכר!", "sentence": "She was unfamiliar with the local customs.|היא לא הייתה מוכרת עם המנהגים המקומיים."},
  "unfortunately": {"assoc": "אנפורצ'ונטלי – אן + פורצ'ון (מזל) = לצערנו, בלי מזל!", "sentence": "Unfortunately, the flight was cancelled.|לצערנו, הטיסה בוטלה."},
  "unimaginable": {"assoc": "אנימג'ינבל – אן + אימג'ין = מעבר לדמיון, בלתי נדמה!", "sentence": "The destruction caused by the storm was unimaginable.|ההרס שנגרם מהסערה היה בלתי נדמה."}
}